lctimer/__init__.py
lctimer/timer.py
lctimer-1.0.0.dist-info/DESCRIPTION.rst
lctimer-1.0.0.dist-info/METADATA
lctimer-1.0.0.dist-info/RECORD
lctimer-1.0.0.dist-info/WHEEL
lctimer-1.0.0.dist-info/metadata.json
lctimer-1.0.0.dist-info/top_level.txt
