Metadata-Version: 2.0
Name: lctimer
Version: 1.0.0
Summary: Set up timer for code assessment
Home-page: UNKNOWN
Author: Lucien Cho
Author-email: zhaoyao@kingsoft.cn
License: MIT
Keywords: lctimer timer
Platform: UNKNOWN
